tabular_pipeline/__init__.py
tabular_pipeline/pipeline.py
tabular_pipeline/read.py
tabular_pipeline/schemas.py
tabular_pipeline/settings.py
tabular_pipeline/steps/__init__.py
tabular_pipeline/steps/conform.py
tabular_pipeline/steps/load.py
tabular_pipeline/util.py
tabular_pipeline/write.py
tabular_pipeline-0.2.3.dist-info/METADATA
tabular_pipeline-0.2.3.dist-info/WHEEL
tabular_pipeline-0.2.3.dist-info/RECORD
