Metadata-Version: 2.1
Name: tabular-pipeline
Version: 0.2.3
Summary: 
Author: franciscobmacedo
Author-email: franciscovcbm@gmail.com
Requires-Python: >=3.10,<4.0
Classifier: Programming Language :: Python :: 3
Classifier: Programming Language :: Python :: 3.10
Classifier: Programming Language :: Python :: 3.11
Requires-Dist: pydantic (>=1.10.8,<2.0.0)
Requires-Dist: pyyaml (>=6.0,<7.0)
Requires-Dist: tablib[xlsx] (>=3.4.0,<4.0.0)
